[{"name": "Linea 1", "color": "red", "start": "Los Dominicos", "end": "San Pablo", "express": false},
 {"name": "Linea 2", "color": "yellow", "start": "La Cisterna", "end": "Vespucio Norte", "express": true},
 {"name": "Linea 4", "color": "blue", "start": "Puente Alto", "end": "Tobalaba", "express": true},
 {"name": "Linea 4A", "color": "sky blue", "start": "La Cisterna", "end": "Vicuña Mackenna", "express": false},
 {"name": "Linea 5", "color": "green", "start": "Vicente Valdes", "end": "Plaza de Maipu", "express": true}]